liqa-1.3.4.data/scripts/PreProcess.pl
liqa-1.3.4.data/scripts/PreProcess_gtf.pl
liqa-1.3.4.data/scripts/group_process.pl
liqa-1.3.4.data/scripts/liqa.py
liqa-1.3.4.data/scripts/noveliso.py
liqa-1.3.4.data/scripts/testDAS.R
liqa_src/PreProcess.pl
liqa_src/PreProcess_gtf.pl
liqa_src/group_process.pl
liqa_src/liqa.py
liqa_src/my_functions.py
liqa_src/noveliso.py
liqa_src/quantify.py
liqa_src/testDAS.R
liqa-1.3.4.dist-info/LICENSE
liqa-1.3.4.dist-info/METADATA
liqa-1.3.4.dist-info/WHEEL
liqa-1.3.4.dist-info/entry_points.txt
liqa-1.3.4.dist-info/top_level.txt
liqa-1.3.4.dist-info/RECORD
