Metadata-Version: 2.1
Name: liqa
Version: 1.3.4
Summary: A statistical tool to quantify isoform-specific expression using long-read RNA-seq
Home-page: https://github.com/WGLab/LIQA
Author: Yu Hu
Author-email: huyu999999@gmail.com
License: MIT
Classifier: Programming Language :: Python :: 3
Classifier: License :: OSI Approved :: MIT License
Classifier: Operating System :: OS Independent
License-File: LICENSE
Requires-Dist: pysam
Requires-Dist: lifelines
